README.rst
datainventory/__init__.py
datainventory/cli.py
datainventory/core.py
datainventory/formats/__init__.py
datainventory/formats/ascii.py
datainventory/formats/csv.py
datainventory/iterate.py
datainventory/sources/__init__.py
datainventory/sources/csv.py
datainventory/sources/sql.py
datainventory/testing.py
data_inventory_tool-0.1.5.dist-info/entry_points.txt
data_inventory_tool-0.1.5.dist-info/WHEEL
data_inventory_tool-0.1.5.dist-info/METADATA
data_inventory_tool-0.1.5.dist-info/RECORD
