Metadata-Version: 2.1
Name: data-inventory-tool
Version: 0.1.5
Summary: Extracts data structure from various sources.
License: MIT
Author: Mantas
Author-email: sirexas@gmail.com
Requires-Python: >=3.8,<4.0
Classifier: License :: OSI Approved :: MIT License
Classifier: Programming Language :: Python :: 3
Classifier: Programming Language :: Python :: 3.8
Requires-Dist: click (>=7.1.2,<8.0.0)
Requires-Dist: sqlalchemy (>=1.3.17,<2.0.0)
